adder_s/__init__.py
adder_s/example.py
adder_s-0.1.dist-info/LICENSE
adder_s-0.1.dist-info/METADATA
adder_s-0.1.dist-info/WHEEL
adder_s-0.1.dist-info/entry_points.txt
adder_s-0.1.dist-info/top_level.txt
adder_s-0.1.dist-info/RECORD
