Metadata-Version: 2.1
Name: adder-s
Version: 0.1
License-File: LICENSE
Requires-Dist: click
